setup.py
mutable_strings/__init__.py
mutable_strings.egg-info/PKG-INFO
mutable_strings.egg-info/SOURCES.txt
mutable_strings.egg-info/dependency_links.txt
mutable_strings.egg-info/not-zip-safe
mutable_strings.egg-info/top_level.txt