Metadata-Version: 1.1
Name: mutable-strings
Version: 1.1
Summary: mutable_strings package give MutStr class with mutable string object and strings methods for it.
Home-page: https://github.com/Daniil-Kost/mutable_strings
Author: Daniil Kostyshak
Author-email: lemk@ukr.net
License: MIT
Platform: UNKNOWN
Classifier: Programming Language :: Python :: 3
Classifier: License :: OSI Approved :: MIT License
